pixelToBinary/__init__.py
pixelToBinary/binary.py
pixelToBinary/image.py
pixelToBinary/utils.py
pixelToBinary/video.py
pixelToBinary-0.0.7.dist-info/LICENSE
pixelToBinary-0.0.7.dist-info/METADATA
pixelToBinary-0.0.7.dist-info/WHEEL
pixelToBinary-0.0.7.dist-info/top_level.txt
pixelToBinary-0.0.7.dist-info/RECORD
