Metadata-Version: 2.1
Name: pixelToBinary
Version: 0.0.7
Summary: A modular python library for creating Binary Images and Binary Movies, easily.
Home-page: https://github.com/Akif-G/pixelToBinary
Author: Akif Gultekin
Author-email: akif.gultekin99@gmail.com
License: UNKNOWN
Platform: UNKNOWN
Classifier: Programming Language :: Python :: 3
Classifier: License :: OSI Approved :: MIT License
Classifier: Operating System :: OS Independent
Requires-Python: >=3.6.9
